[
  {
    "code": "7203",
    "name": "トヨタ自動車(株)",
    "price": 3713.0,
    "per": 13.131953,
    "pbr": 1.247336,
    "roe": 0.10032,
    "dividendYield": 2.56
  },
  {
    "code": "8306",
    "name": "(株)三菱ＵＦＪフィナンシャル・グループ",
    "price": 2876.5,
    "per": 17.53922,
    "pbr": 1.566016,
    "roe": 0.06113,
    "dividendYield": 2.71
  },
  {
    "code": "9984",
    "name": "ソフトバンクグループ(株)",
    "price": 4449.0,
    "per": 8.089458,
    "pbr": 1.596125,
    "roe": 0.26023,
    "dividendYield": 0.25
  },
  {
    "code": "8316",
    "name": "(株)三井住友フィナンシャルグループ",
    "price": 5716.0,
    "per": 15.723725,
    "pbr": 1.4376467,
    "roe": 0.04933,
    "dividendYield": 2.75
  },
  {
    "code": "6501",
    "name": "(株)日立製作所",
    "price": 4897.0,
    "per": 29.414934,
    "pbr": 3.4946923,
    "roe": null,
    "dividendYield": 0.92
  },
  {
    "code": "9983",
    "name": "(株)ファーストリテイリング",
    "price": 67410.0,
    "per": 47.924934,
    "pbr": 8.273264,
    "roe": 0.20033,
    "dividendYield": 0.8
  },
  {
    "code": "6758",
    "name": "ソニーグループ(株)",
    "price": 3487.0,
    "per": 16.824106,
    "pbr": 2.539123,
    "roe": 0.14917,
    "dividendYield": 0.72
  },
  {
    "code": "6857",
    "name": "(株)アドバンテスト",
    "price": 26795.0,
    "per": 75.65171,
    "pbr": 29.035767,
    "roe": 0.49263,
    "dividendYield": 0.18
  },
  {
    "code": "8035",
    "name": "東京エレクトロン(株)",
    "price": 42150.0,
    "per": 36.896572,
    "pbr": 9.91907,
    "roe": 0.26457,
    "dividendYield": 1.43
  },
  {
    "code": "8058",
    "name": "三菱商事(株)",
    "price": 4890.0,
    "per": 27.990404,
    "pbr": 1.9947923,
    "roe": 0.08528,
    "dividendYield": 2.25
  },
  {
    "code": "8411",
    "name": "(株)みずほフィナンシャルグループ",
    "price": 7000.0,
    "per": 16.661928,
    "pbr": 1.5545521,
    "roe": 0.09653,
    "dividendYield": 2.07
  },
  {
    "code": "8001",
    "name": "伊藤忠商事(株)",
    "price": 2151.0,
    "per": 16.62153,
    "pbr": 2.7734785,
    "roe": 0.14241,
    "dividendYield": 2.05
  },
  {
    "code": "7011",
    "name": "三菱重工業(株)",
    "price": 4820.0,
    "per": 60.790573,
    "pbr": 6.27184,
    "roe": null,
    "dividendYield": 0.5
  },
  {
    "code": "8031",
    "name": "三井物産(株)",
    "price": 5430.0,
    "per": 17.268923,
    "pbr": 1.8471917,
    "roe": 0.10781,
    "dividendYield": 2.21
  },
  {
    "code": "4519",
    "name": "中外製薬(株)",
    "price": 9170.0,
    "per": 35.59258,
    "pbr": 7.636602,
    "roe": 0.22103001,
    "dividendYield": 1.44
  },
  {
    "code": "6861",
    "name": "(株)キーエンス",
    "price": 58190.0,
    "per": 34.6072,
    "pbr": 4.2464194,
    "roe": null,
    "dividendYield": 0.95
  },
  {
    "code": "9432",
    "name": "ＮＴＴ(株)",
    "price": 153.10000610351562,
    "per": 12.191235,
    "pbr": 1.3147379,
    "roe": 0.10722999,
    "dividendYield": 3.46
  },
  {
    "code": "8766",
    "name": "東京海上ホールディングス(株)",
    "price": 6248.0,
    "per": 11.782038,
    "pbr": 2.3136137,
    "roe": 0.20663999,
    "dividendYield": 3.38
  },
  {
    "code": "2914",
    "name": "ＪＴ",
    "price": 5891.0,
    "per": 21.2242,
    "pbr": 2.5907974,
    "roe": 0.12149999,
    "dividendYield": 4.11
  },
  {
    "code": "6503",
    "name": "三菱電機(株)",
    "price": 5467.0,
    "per": 29.481133,
    "pbr": 2.771982,
    "roe": 0.09513,
    "dividendYield": 1.01
  },
  {
    "code": "9433",
    "name": "ＫＤＤＩ(株)",
    "price": 2670.0,
    "per": 14.826289,
    "pbr": 2.0541844,
    "roe": 0.1423,
    "dividendYield": 3.0
  },
  {
    "code": "7974",
    "name": "任天堂(株)",
    "price": 8409.0,
    "per": 27.241184,
    "pbr": 3.3793974,
    "roe": 0.14130001,
    "dividendYield": 2.15
  },
  {
    "code": "4063",
    "name": "信越化学工業(株)",
    "price": 5423.0,
    "per": 21.512415,
    "pbr": 2.4059365,
    "roe": 0.11484,
    "dividendYield": 1.95
  },
  {
    "code": "7182",
    "name": "(株)ゆうちょ銀行",
    "price": 2964.0,
    "per": 24.630215,
    "pbr": 1.1304443,
    "roe": 0.05311,
    "dividendYield": 2.36
  },
  {
    "code": "9434",
    "name": "ソフトバンク(株)",
    "price": 214.5,
    "per": 19.030249,
    "pbr": 3.5762053,
    "roe": 0.17556,
    "dividendYield": 4.01
  },
  {
    "code": "6098",
    "name": "(株)リクルートホールディングス",
    "price": 6114.0,
    "per": 21.292992,
    "pbr": 5.7022552,
    "roe": 0.2732,
    "dividendYield": 0.41
  },
  {
    "code": "8002",
    "name": "丸紅(株)",
    "price": 5748.0,
    "per": 16.804625,
    "pbr": 2.2960582,
    "roe": 0.12854,
    "dividendYield": 1.87
  },
  {
    "code": "4502",
    "name": "武田薬品工業(株)",
    "price": 5557.0,
    "per": 82.31543,
    "pbr": 1.2005683,
    "roe": 0.01503,
    "dividendYield": 3.6
  },
  {
    "code": "7741",
    "name": "ＨＯＹＡ(株)",
    "price": 27420.0,
    "per": 44.544292,
    "pbr": 8.935816,
    "roe": 0.24176,
    "dividendYield": 0.88
  },
  {
    "code": "7267",
    "name": "ホンダ",
    "price": 1570.5,
    "per": 12.690457,
    "pbr": 0.49415445,
    "roe": 0.042969998,
    "dividendYield": 4.46
  },
  {
    "code": "8053",
    "name": "住友商事(株)",
    "price": 6549.0,
    "per": 13.042787,
    "pbr": 1.7313042,
    "roe": 0.12635,
    "dividendYield": 2.14
  },
  {
    "code": "6146",
    "name": "(株)ディスコ",
    "price": 71720.0,
    "per": 61.823284,
    "pbr": 14.363552,
    "roe": null,
    "dividendYield": 0.61
  },
  {
    "code": "6702",
    "name": "富士通(株)",
    "price": 3700.0,
    "per": 22.647419,
    "pbr": 3.2389808,
    "roe": 0.16861,
    "dividendYield": 1.35
  },
  {
    "code": "8015",
    "name": "豊田通商(株)",
    "price": 6554.0,
    "per": 19.399431,
    "pbr": 2.3713214,
    "roe": 0.135,
    "dividendYield": 1.77
  },
  {
    "code": "6981",
    "name": "(株)村田製作所",
    "price": 3509.0,
    "per": 34.994183,
    "pbr": 2.5134604,
    "roe": 0.07253,
    "dividendYield": 1.71
  },
  {
    "code": "6301",
    "name": "コマツ",
    "price": 7602.0,
    "per": 16.91818,
    "pbr": 2.0460925,
    "roe": 0.12517999,
    "dividendYield": 2.5
  },
  {
    "code": "5802",
    "name": "住友電気工業(株)",
    "price": 8651.0,
    "per": 31.882383,
    "pbr": 2.7674384,
    "roe": 0.110249996,
    "dividendYield": 1.36
  },
  {
    "code": "6902",
    "name": "(株)デンソー",
    "price": 2255.0,
    "per": 18.084604,
    "pbr": 1.170534,
    "roe": 0.07893,
    "dividendYield": 2.84
  },
  {
    "code": "8267",
    "name": "イオン(株)",
    "price": 2360.0,
    "per": 211.87114,
    "pbr": 5.7458334,
    "roe": 0.03787,
    "dividendYield": 1.14
  },
  {
    "code": "5803",
    "name": "(株)フジクラ",
    "price": 21420.0,
    "per": 47.623108,
    "pbr": 12.158081,
    "roe": 0.31145,
    "dividendYield": 1.12
  },
  {
    "code": "6201",
    "name": "(株)豊田自動織機",
    "price": 20200.0,
    "per": 29.651707,
    "pbr": 0.9979631,
    "roe": null,
    "dividendYield": 1.39
  },
  {
    "code": "8725",
    "name": "ＭＳ＆ＡＤインシュアランスグループホールディングス(株)",
    "price": 4202.0,
    "per": 8.982358,
    "pbr": 1.3873751,
    "roe": 0.16309999,
    "dividendYield": 2.86
  },
  {
    "code": "7751",
    "name": "キヤノン(株)",
    "price": 4786.0,
    "per": 13.100329,
    "pbr": 1.2100627,
    "roe": 0.096549995,
    "dividendYield": 3.34
  },
  {
    "code": "8591",
    "name": "オリックス(株)",
    "price": 5288.0,
    "per": 13.009671,
    "pbr": 1.3086436,
    "roe": 0.106850006,
    "dividendYield": 3.55
  },
  {
    "code": "6954",
    "name": "ファナック(株)",
    "price": 6509.0,
    "per": 37.762486,
    "pbr": 3.3089623,
    "roe": 0.093660004,
    "dividendYield": 1.58
  },
  {
    "code": "6752",
    "name": "パナソニック　ホールディングス(株)",
    "price": 2351.5,
    "per": 18.106094,
    "pbr": 1.1509644,
    "roe": 0.04152,
    "dividendYield": 1.7
  },
  {
    "code": "3382",
    "name": "(株)セブン＆アイ・ホールディングス",
    "price": 2327.0,
    "per": 24.48137,
    "pbr": 1.572465,
    "roe": 0.085839994,
    "dividendYield": 2.15
  },
  {
    "code": "6367",
    "name": "ダイキン工業(株)",
    "price": 19885.0,
    "per": 21.613525,
    "pbr": 1.8760667,
    "roe": 0.0929,
    "dividendYield": 1.66
  },
  {
    "code": "8802",
    "name": "三菱地所(株)",
    "price": 4820.0,
    "per": 30.672216,
    "pbr": 2.3320282,
    "roe": 0.09404001,
    "dividendYield": 0.95
  }
]